grokcore.content-4.2-py3.12-nspkg.pth
grokcore/content/__init__.py
grokcore/content/components.py
grokcore/content/interfaces.py
grokcore/content/tests/__init__.py
grokcore/content/tests/test_container.py
grokcore/content/tests/test_container_event.py
grokcore/content/tests/test_orderedcontainer.py
grokcore/content/tests/test_verify_containers.py
grokcore_content-4.2.dist-info/licenses/LICENSE.txt
grokcore_content-4.2.dist-info/METADATA
grokcore_content-4.2.dist-info/WHEEL
grokcore_content-4.2.dist-info/namespace_packages.txt
grokcore_content-4.2.dist-info/top_level.txt
grokcore_content-4.2.dist-info/RECORD
