Metadata-Version: 2.4
Name: grokcore.content
Version: 4.2
Summary: Base content types for Grok
Home-page: https://github.com/zopefoundation/grokcore.content
Download-URL: https://pypi.org/project/grokcore.content
Author: Grok Team
Author-email: zope-dev@zope.dev
License: ZPL
Classifier: Environment :: Web Environment
Classifier: Intended Audience :: Developers
Classifier: Framework :: Zope :: 3
Classifier: License :: OSI Approved :: Zope Public License
Classifier: Programming Language :: Python
Classifier: Programming Language :: Python :: 3
Classifier: Programming Language :: Python :: 3.9
Classifier: Programming Language :: Python :: 3.10
Classifier: Programming Language :: Python :: 3.11
Classifier: Programming Language :: Python :: 3.12
Classifier: Programming Language :: Python :: 3.13
Classifier: Programming Language :: Python :: Implementation :: CPython
Classifier: Programming Language :: Python :: Implementation :: PyPy
Requires-Python: >=3.9
License-File: LICENSE.txt
Requires-Dist: setuptools
Requires-Dist: persistent
Requires-Dist: grokcore.component>=2.1
Requires-Dist: zope.annotation
Requires-Dist: zope.container
Requires-Dist: zope.interface
Requires-Dist: zope.lifecycleevent
Provides-Extra: test
Requires-Dist: zope.component; extra == "test"
Requires-Dist: zope.testing; extra == "test"
Requires-Dist: zope.testrunner; extra == "test"
Dynamic: author
Dynamic: author-email
Dynamic: classifier
Dynamic: description
Dynamic: download-url
Dynamic: home-page
Dynamic: license
Dynamic: license-file
Dynamic: provides-extra
Dynamic: requires-dist
Dynamic: requires-python
Dynamic: summary
